{
  "__inputs": [
    {
      "name": "DS_BEEGFS_MON_INFLUXDB",
      "label": "beegfs_mon_influxdb",
      "description": "",
      "type": "datasource",
      "pluginId": "influxdb",
      "pluginName": "InfluxDB"
    }
  ],
  "__elements": {},
  "__requires": [
    {
      "type": "grafana",
      "id": "grafana",
      "name": "Grafana",
      "version": "9.3.0"
    },
    {
      "type": "datasource",
      "id": "influxdb",
      "name": "InfluxDB",
      "version": "1.0.0"
    },
    {
      "type": "panel",
      "id": "table",
      "name": "Table",
      "version": ""
    },
    {
      "type": "panel",
      "id": "timeseries",
      "name": "Time series",
      "version": ""
    }
  ],
  "annotations": {
    "list": [
      {
        "builtIn": 1,
        "datasource": {
          "type": "grafana",
          "uid": "-- Grafana --"
        },
        "enable": true,
        "hide": true,
        "iconColor": "rgba(0, 211, 255, 1)",
        "name": "Annotations & Alerts",
        "target": {
          "limit": 100,
          "matchAny": false,
          "tags": [],
          "type": "dashboard"
        },
        "type": "dashboard"
      }
    ]
  },
  "editable": true,
  "fiscalYearStartMonth": 0,
  "graphTooltip": 2,
  "id": null,
  "links": [],
  "liveNow": false,
  "panels": [
    {
      "datasource": {
        "type": "influxdb",
        "uid": "${DS_BEEGFS_MON_INFLUXDB}"
      },
      "description": "Top clients by current watched inode count on the selected meta. Last value within the time range.",
      "fieldConfig": {
        "defaults": {
          "color": {
            "mode": "thresholds"
          },
          "custom": {
            "align": "center",
            "displayMode": "auto",
            "inspect": false
          },
          "mappings": [],
          "thresholds": {
            "mode": "absolute",
            "steps": [
              {
                "color": "green",
                "value": null
              },
              {
                "color": "orange",
                "value": 100000
              },
              {
                "color": "red",
                "value": 1000000
              }
            ]
          },
          "unit": "short"
        },
        "overrides": [
          {
            "matcher": {
              "id": "byName",
              "options": "Watched Inodes"
            },
            "properties": [
              {
                "id": "custom.displayMode",
                "value": "gradient-gauge"
              }
            ]
          }
        ]
      },
      "gridPos": {
        "h": 10,
        "w": 24,
        "x": 0,
        "y": 0
      },
      "id": 2,
      "options": {
        "cellHeight": "sm",
        "footer": {
          "countRows": false,
          "fields": "",
          "reducer": [
            "sum"
          ],
          "show": false
        },
        "frameIndex": 0,
        "showHeader": true,
        "sortBy": [
          {
            "desc": true,
            "displayName": "Watched Inodes"
          }
        ]
      },
      "pluginVersion": "9.3.0",
      "targets": [
        {
          "alias": "Watched Inodes",
          "datasource": {
            "type": "influxdb",
            "uid": "${DS_BEEGFS_MON_INFLUXDB}"
          },
          "groupBy": [],
          "measurement": "invalWatchPerClient",
          "orderByTime": "ASC",
          "policy": "default",
          "query": "from(bucket: \"${bucket}\")  |> range(start: v.timeRangeStart, stop: v.timeRangeStop)  |> filter(fn: (r) =>    r.nodeNumID == \"${metaID}\" and    r._measurement == \"invalWatchPerClient\" and    r._field == \"watchedInodeCount\")  |> group(columns: [\"clientId\"])  |> last()  |> group()  |> keep(columns: [\"clientId\", \"_value\"])  |> rename(columns: {_value: \"Watched Inodes\"})  |> sort(columns: [\"Watched Inodes\"], desc: true)  |> limit(n: 50)",
          "rawQuery": true,
          "refId": "A",
          "resultFormat": "table"
        }
      ],
      "title": "Top Clients by Watched Inodes (meta ${metaID})",
      "transformations": [
        {
          "id": "organize",
          "options": {
            "excludeByName": {},
            "indexByName": {
              "Watched Inodes": 1,
              "clientId": 0
            },
            "renameByName": {}
          }
        }
      ],
      "type": "table"
    },
    {
      "datasource": {
        "type": "influxdb",
        "uid": "${DS_BEEGFS_MON_INFLUXDB}"
      },
      "description": "Watched inode count per client over time. Stacked to show total watched inodes by client.",
      "fieldConfig": {
        "defaults": {
          "color": {
            "mode": "palette-classic"
          },
          "custom": {
            "axisCenteredZero": false,
            "axisColorMode": "text",
            "axisLabel": "",
            "axisPlacement": "auto",
            "barAlignment": 0,
            "drawStyle": "line",
            "fillOpacity": 60,
            "gradientMode": "opacity",
            "hideFrom": {
              "legend": false,
              "tooltip": false,
              "viz": false
            },
            "lineInterpolation": "linear",
            "lineWidth": 1,
            "pointSize": 5,
            "scaleDistribution": {
              "type": "linear"
            },
            "showPoints": "never",
            "spanNulls": true,
            "stacking": {
              "group": "A",
              "mode": "none"
            },
            "thresholdsStyle": {
              "mode": "off"
            }
          },
          "displayName": "${__field.labels.clientId}",
          "mappings": [],
          "thresholds": {
            "mode": "absolute",
            "steps": [
              {
                "color": "green",
                "value": null
              }
            ]
          },
          "unit": "short"
        },
        "overrides": []
      },
      "gridPos": {
        "h": 10,
        "w": 12,
        "x": 0,
        "y": 10
      },
      "id": 3,
      "options": {
        "legend": {
          "calcs": [
            "max",
            "lastNotNull"
          ],
          "displayMode": "table",
          "placement": "bottom",
          "showLegend": true
        },
        "tooltip": {
          "mode": "multi",
          "sort": "desc"
        }
      },
      "targets": [
        {
          "datasource": {
            "type": "influxdb",
            "uid": "${DS_BEEGFS_MON_INFLUXDB}"
          },
          "groupBy": [],
          "measurement": "invalWatchPerClient",
          "orderByTime": "ASC",
          "policy": "default",
          "query": "from(bucket: \"${bucket}\")  |> range(start: v.timeRangeStart, stop: v.timeRangeStop)  |> filter(fn: (r) =>    r.nodeNumID == \"${metaID}\" and    r._measurement == \"invalWatchPerClient\" and    r._field == \"watchedInodeCount\" and    contains(value: r.clientId, set: ${clientId:json}))  |> group(columns: [\"clientId\"])  |> aggregateWindow(every: v.windowPeriod, fn: max, createEmpty: false)  |> rename(columns: {_value: \"watchedInodeCount\"})",
          "rawQuery": true,
          "refId": "A",
          "resultFormat": "time_series"
        }
      ],
      "title": "Watched Inodes per Client",
      "type": "timeseries"
    },
    {
      "datasource": {
        "type": "influxdb",
        "uid": "${DS_BEEGFS_MON_INFLUXDB}"
      },
      "description": "Per-second invalidation rate per client (non-negative derivative of the cumulative numInvalidations counter).",
      "fieldConfig": {
        "defaults": {
          "color": {
            "mode": "palette-classic"
          },
          "custom": {
            "axisCenteredZero": false,
            "axisColorMode": "text",
            "axisLabel": "",
            "axisPlacement": "auto",
            "barAlignment": 0,
            "drawStyle": "line",
            "fillOpacity": 10,
            "gradientMode": "opacity",
            "hideFrom": {
              "legend": false,
              "tooltip": false,
              "viz": false
            },
            "lineInterpolation": "linear",
            "lineWidth": 1,
            "pointSize": 5,
            "scaleDistribution": {
              "type": "linear"
            },
            "showPoints": "never",
            "spanNulls": true,
            "stacking": {
              "group": "A",
              "mode": "none"
            },
            "thresholdsStyle": {
              "mode": "off"
            }
          },
          "displayName": "${__field.labels.clientId}",
          "mappings": [],
          "thresholds": {
            "mode": "absolute",
            "steps": [
              {
                "color": "green",
                "value": null
              }
            ]
          },
          "unit": "ops"
        },
        "overrides": []
      },
      "gridPos": {
        "h": 10,
        "w": 12,
        "x": 12,
        "y": 10
      },
      "id": 4,
      "options": {
        "legend": {
          "calcs": [
            "max",
            "lastNotNull"
          ],
          "displayMode": "table",
          "placement": "bottom",
          "showLegend": true
        },
        "tooltip": {
          "mode": "multi",
          "sort": "desc"
        }
      },
      "targets": [
        {
          "datasource": {
            "type": "influxdb",
            "uid": "${DS_BEEGFS_MON_INFLUXDB}"
          },
          "groupBy": [],
          "measurement": "invalWatchPerClient",
          "orderByTime": "ASC",
          "policy": "default",
          "query": "from(bucket: \"${bucket}\")  |> range(start: v.timeRangeStart, stop: v.timeRangeStop)  |> filter(fn: (r) =>    r.nodeNumID == \"${metaID}\" and    r._measurement == \"invalWatchPerClient\" and    r._field == \"numInvalidations\" and    contains(value: r.clientId, set: ${clientId:json}))  |> group(columns: [\"clientId\"])  |> aggregateWindow(every: v.windowPeriod, fn: max, createEmpty: false)  |> derivative(unit: 1s, nonNegative: true)  |> rename(columns: {_value: \"invalidations/s\"})",
          "rawQuery": true,
          "refId": "A",
          "resultFormat": "time_series"
        }
      ],
      "title": "Invalidation Rate per Client",
      "type": "timeseries"
    }
  ],
  "refresh": "",
  "schemaVersion": 37,
  "style": "dark",
  "tags": [],
  "templating": {
    "list": [
      {
        "current": {},
        "datasource": {
          "type": "influxdb",
          "uid": "${DS_BEEGFS_MON_INFLUXDB}"
        },
        "definition": "buckets()",
        "hide": 0,
        "includeAll": false,
        "label": "Bucket",
        "multi": false,
        "name": "bucket",
        "options": [],
        "query": "buckets()",
        "refresh": 1,
        "regex": "",
        "skipUrlSync": false,
        "sort": 0,
        "type": "query"
      },
      {
        "current": {},
        "datasource": {
          "type": "influxdb",
          "uid": "${DS_BEEGFS_MON_INFLUXDB}"
        },
        "definition": "import \"influxdata/influxdb/schema\"schema.measurementTagValues(  bucket: \"${bucket}\",  tag: \"nodeNumID\",  measurement: \"invalWatchPerClient\")",
        "hide": 0,
        "includeAll": false,
        "label": "metaID",
        "multi": false,
        "name": "metaID",
        "options": [],
        "query": "import \"influxdata/influxdb/schema\"schema.measurementTagValues(  bucket: \"${bucket}\",  tag: \"nodeNumID\",  measurement: \"invalWatchPerClient\")",
        "refresh": 1,
        "regex": "",
        "skipUrlSync": false,
        "sort": 0,
        "type": "query"
      },
      {
        "current": {},
        "datasource": {
          "type": "influxdb",
          "uid": "${DS_BEEGFS_MON_INFLUXDB}"
        },
        "definition": "import \"influxdata/influxdb/schema\"schema.measurementTagValues(  bucket: \"${bucket}\",  tag: \"clientId\",  measurement: \"invalWatchPerClient\")",
        "hide": 0,
        "includeAll": true,
        "label": "clientId",
        "multi": true,
        "name": "clientId",
        "options": [],
        "query": "import \"influxdata/influxdb/schema\"schema.measurementTagValues(  bucket: \"${bucket}\",  tag: \"clientId\",  measurement: \"invalWatchPerClient\")",
        "refresh": 1,
        "regex": "",
        "skipUrlSync": false,
        "sort": 1,
        "type": "query"
      }
    ]
  },
  "time": {
    "from": "now-6h",
    "to": "now"
  },
  "timepicker": {},
  "timezone": "",
  "title": "BeeGFS Meta InvalWatch (Per-Client)",
  "uid": "beegfs-meta-inode-cache-v2",
  "version": 1,
  "weekStart": ""
}